tests/__init__.py
tests/test_modeldb_methods.py
tests/test_track_methods.py
trait2d/__init__.py
trait2d/detectors.py
trait2d/exceptions.py
trait2d/movie_processor.py
trait2d/simulators.py
trait2d/tracker.py
trait2d/analysis/__init__.py
trait2d/analysis/_adc.py
trait2d/analysis/_msd.py
trait2d/analysis/models.py
trait2d_analysis_gui/__init__.py
trait2d_analysis_gui/dialog_import.ui
trait2d_analysis_gui/dialog_trackid.ui
trait2d_analysis_gui/gui_analysis.ui
trait2d_analysis_gui/plot.py
trait2d_analysis_gui/render_math.py
trait2d_analysis_gui/tab/__init__.py
trait2d_analysis_gui/tab/adc.py
trait2d_analysis_gui/tab/adc.ui
trait2d_analysis_gui/tab/msd.py
trait2d_analysis_gui/tab/msd.ui
trait2d_simulator_gui/__init__.py
trait2d_tracker_gui/__init__.py
trait2d-1.2.1.dist-info/LICENSE
trait2d-1.2.1.dist-info/METADATA
trait2d-1.2.1.dist-info/WHEEL
trait2d-1.2.1.dist-info/entry_points.txt
trait2d-1.2.1.dist-info/top_level.txt
trait2d-1.2.1.dist-info/RECORD
