Metadata-Version: 2.1
Name: trait2d
Version: 1.2.1
Summary: Cross-platform Python software package and GUIs to support Single Particle Tracking experiments.
Home-page: https://github.com/Eggeling-Lab-Microscope-Software/TRAIT2D
Author: Francesco Reina, John Wigg, Mariia Dmitrieva, Bela Vogler, Joël Lefebvre,
Author-email: f.reina3@gmail.com, john.wigg@uni-jena.de, mariia.dmitrieva@eng.ox.ac.uk, bela.vogler@uni-jena.de, lefebvre.joel@uqam.ca
License: UNKNOWN
Platform: UNKNOWN
Classifier: Programming Language :: Python :: 3
Classifier: License :: OSI Approved :: GNU General Public License v3 (GPLv3)
Classifier: Operating System :: OS Independent
Requires-Python: >=3.7
License-File: LICENSE
Requires-Dist: setuptools
Requires-Dist: wheel
Requires-Dist: numpy
Requires-Dist: scipy
Requires-Dist: scikit-image
Requires-Dist: matplotlib
Requires-Dist: opencv-python
Requires-Dist: tqdm
Requires-Dist: pandas
Requires-Dist: tk
Requires-Dist: imageio
Requires-Dist: PyQt5
Requires-Dist: pyqtgraph
